README.md
setup.py
surrogate/__init__.py
surrogate/surrogate.py
surrogate.egg-info/PKG-INFO
surrogate.egg-info/SOURCES.txt
surrogate.egg-info/dependency_links.txt
surrogate.egg-info/not-zip-safe
surrogate.egg-info/top_level.txt